dcszap.py
dcszap-0.4.3.dist-info/LICENSE
dcszap-0.4.3.dist-info/METADATA
dcszap-0.4.3.dist-info/WHEEL
dcszap-0.4.3.dist-info/entry_points.txt
dcszap-0.4.3.dist-info/top_level.txt
dcszap-0.4.3.dist-info/RECORD
