Metadata-Version: 2.1
Name: dcszap
Version: 0.4.3
Summary: DCS-BIOS client to automate aircraft setup
Author-email: Jack Deeth <developer@jackdeeth.org.uk>
License: MIT License
Project-URL: Homepage, https://github.com/JDeeth/DCSZap
Project-URL: Bug Tracker, https://github.com/JDeeth/DCSZap/issues
Keywords: DCS,DCSWorld,digital-combat-simulator,automation,flightsim
Classifier: Programming Language :: Python
Classifier: Programming Language :: Python :: 3
Classifier: License :: OSI Approved :: MIT License
Classifier: Operating System :: OS Independent
Classifier: Environment :: Console
Classifier: Topic :: Games/Entertainment
Classifier: Topic :: Games/Entertainment :: Simulation
Classifier: Topic :: Utilities
Requires-Python: >=3.7
License-File: LICENSE
Provides-Extra: dev
Requires-Dist: coverage ; extra == 'dev'
Requires-Dist: mock ; extra == 'dev'
Requires-Dist: pytest ; extra == 'dev'
Requires-Dist: pytest-cov ; extra == 'dev'
Requires-Dist: pytest-mock ; extra == 'dev'
Requires-Dist: hypothesis ; extra == 'dev'
Requires-Dist: pylint ; extra == 'dev'
Requires-Dist: black ; extra == 'dev'
Requires-Dist: bumpver ; extra == 'dev'
Requires-Dist: pre-commit ; extra == 'dev'
Requires-Dist: tox ; extra == 'dev'
Provides-Extra: publish
Requires-Dist: setuptools >=61.1.0 ; extra == 'publish'
Requires-Dist: build ; extra == 'publish'
Requires-Dist: twine ; extra == 'publish'
